fastcli/__init__.py
fastcli/__main__.py
fastcli/main.py
fastcli/utils.py
fastapi_fastcli-0.1.8.dist-info/METADATA
fastapi_fastcli-0.1.8.dist-info/WHEEL
fastapi_fastcli-0.1.8.dist-info/entry_points.txt
fastapi_fastcli-0.1.8.dist-info/RECORD
