Metadata-Version: 2.1
Name: fastapi-fastcli
Version: 0.1.8
Summary: FastAPI CLI
Author: Jack Zhai
Author-email: zhaijiawei0828@gmail.com
Requires-Python: >=3.8,<4.0
Classifier: Programming Language :: Python :: 3
Classifier: Programming Language :: Python :: 3.8
Classifier: Programming Language :: Python :: 3.9
Classifier: Programming Language :: Python :: 3.10
Classifier: Programming Language :: Python :: 3.11
Classifier: Programming Language :: Python :: 3.12
Requires-Dist: fastapi (>=0.100)
Requires-Dist: rich (>=13)
Requires-Dist: typer (>=0.9.0)
Requires-Dist: uvicorn (>=0.23)
